<?xml version="1.0" encoding="utf-8" ?>
<dwsync>
<file name="img_2410.jpg" server="livebolivar.com" local="131427102400301285" remote="131427061800000000" />
<file name="rs_img_2372.jpg" server="livebolivar.com" local="131427099261313256" remote="131427061800000000" />
<file name="rs_img_2386.jpg" server="livebolivar.com" local="131427099311530286" remote="131427061800000000" />
<file name="rs_img_2387.jpg" server="livebolivar.com" local="131427099315071999" remote="131427061800000000" />
<file name="rs_img_2388.jpg" server="livebolivar.com" local="131427099318701598" remote="131427061800000000" />
<file name="rs_img_2391.jpg" server="livebolivar.com" local="131427099329053876" remote="131427061800000000" />
<file name="rs_img_2392.jpg" server="livebolivar.com" local="131427099332879432" remote="131427061800000000" />
<file name="rs_img_2393.jpg" server="livebolivar.com" local="131427099336108184" remote="131427061800000000" />
<file name="rs_img_2396.jpg" server="livebolivar.com" local="131427099346436768" remote="131427061800000000" />
<file name="rs_img_2399.jpg" server="livebolivar.com" local="131427099353920888" remote="131427061800000000" />
<file name="rs_img_2400.jpg" server="livebolivar.com" local="131427099357148807" remote="131427061800000000" />
<file name="rs_img_2402.jpg" server="livebolivar.com" local="131427099364782792" remote="131427061800000000" />
<file name="rs_img_2403.jpg" server="livebolivar.com" local="131427099368165020" remote="131427061800000000" />
<file name="rs_img_2404.jpg" server="livebolivar.com" local="131427099371636871" remote="131427061800000000" />
<file name="rs_img_2405.jpg" server="livebolivar.com" local="131427099375490052" remote="131427061800000000" />
<file name="rs_img_2407.jpg" server="livebolivar.com" local="131427099382348270" remote="131427061800000000" />
</dwsync>